[
    {
        "ranking": "1",
        "title": "Längesen",
        "artist": "Bolaget",
        "image": "https://i.scdn.co/image/ab67616d00001e022a136e9e8cc82aa6d630df8b",
        "peak": "1",
        "prev": "—",
        "streak": "1",
        "streams": "232,115",
        "spotifyID": "40yRQySDfSc5I6SoZzRLxZ"
    },
    {
        "ranking": "2",
        "title": "Last Christmas",
        "artist": "Wham!",
        "image": "https://i.scdn.co/image/ab67616d00001e02f2d2adaa21ad616df6241e7d",
        "peak": "1",
        "prev": "1",
        "streak": "55",
        "streams": "134,892",
        "spotifyID": "2FRnf9qhLbvw8fu4IBXx78",
        "appleID": "last-christmas/282658482",
        "youtubeID": "E8gmARGvPlI"
    },
    {
        "ranking": "3",
        "title": "All I Want for Christmas Is You",
        "artist": "Mariah Carey",
        "image": "https://i.scdn.co/image/ab67616d00001e024246e3158421f5abb75abc4f",
        "peak": "1",
        "prev": "2",
        "streak": "55",
        "streams": "121,811",
        "spotifyID": "0bYg9bo50gSsH3LtXe2SQn",
        "youtubeID": "aAkMkVFwAoo"
    },
    {
        "ranking": "4",
        "title": "Rockin' Around The Christmas Tree",
        "artist": "Brenda Lee",
        "image": "https://i.scdn.co/image/ab67616d00001e027845f74d6db14b400fa61cd3",
        "peak": "3",
        "prev": "3",
        "streak": "47",
        "streams": "121,114",
        "spotifyID": "2EjXfH91m7f8HiJN1yQg97",
        "youtubeID": "TFsZy9t-qDc"
    },
    {
        "ranking": "5",
        "title": "Tänd ett ljus",
        "artist": "Triad",
        "image": "https://i.scdn.co/image/ab67616d00001e027e60c24ad1a05a173534f0e5",
        "peak": "3",
        "prev": "4",
        "streak": "43",
        "streams": "107,418",
        "spotifyID": "0WeT9UnF79pGH5ohYHsnD9",
        "appleID": "t%C3%A4nd-ett-ljus/926176029",
        "youtubeID": "w-Fw484lBeA"
    },
    {
        "ranking": "6",
        "title": "A Christmas Song",
        "artist": "Björnzone",
        "image": "https://i.scdn.co/image/ab67616d00001e025875545184b3b68dc3dea83b",
        "peak": "6",
        "prev": "11",
        "streak": "27",
        "streams": "103,176",
        "spotifyID": "5ta6j4wZw2pb2huu6od7nk",
        "youtubeID": "kpSOWZCSPxo"
    },
    {
        "ranking": "7",
        "title": "Jingle Bell Rock",
        "artist": "Bobby Helms",
        "image": "https://i.scdn.co/image/ab67616d00001e02fd56f3c7a294f5cfe51c7b17",
        "peak": "5",
        "prev": "5",
        "streak": "40",
        "streams": "102,988",
        "spotifyID": "7vQbuQcyTflfCIOu3Uzzya",
        "appleID": "jingle-bell-rock/1358462132",
        "youtubeID": "Z0ajuTaHBtM"
    },
    {
        "ranking": "8",
        "title": "HEAVEN & HELL",
        "artist": "Gaboro",
        "image": "https://i.scdn.co/image/ab67616d00001e025d683747316d74b7cbae2063",
        "peak": "8",
        "prev": "83",
        "streak": "7",
        "streams": "101,199",
        "spotifyID": "6FaMpOVyLVhyf6Fb8QMrhO"
    },
    {
        "ranking": "9",
        "title": "Julen är här",
        "artist": "Tommy Körberg, Sissel",
        "image": "https://i.scdn.co/image/ab67616d00001e026ce80817009552c78bc6157a",
        "peak": "4",
        "prev": "6",
        "streak": "40",
        "streams": "97,167",
        "spotifyID": "4cGPWeCfoQTw7i0wqNRcjI"
    },
    {
        "ranking": "10",
        "title": "Snowman",
        "artist": "Sia",
        "image": "https://i.scdn.co/image/ab67616d00001e02d1410c1372fab1e516328fa8",
        "peak": "5",
        "prev": "14",
        "streak": "40",
        "streams": "90,850",
        "spotifyID": "7uoFMmxln0GPXQ0AcCBXRq",
        "youtubeID": "gset79KMmt0"
    },
    {
        "ranking": "11",
        "title": "It's the Most Wonderful Time of the Year",
        "artist": "Andy Williams",
        "image": "https://i.scdn.co/image/ab67616d00001e02585897779cf3591ba0f07650",
        "peak": "6",
        "prev": "7",
        "streak": "40",
        "streams": "87,909",
        "spotifyID": "1IcR6RlgvDczfvoWJSSY2A",
        "appleID": "its-the-most-wonderful-time-of-the-year/171434594",
        "youtubeID": "cbZTfrhcamA"
    },
    {
        "ranking": "12",
        "title": "Djurens vaggvisa",
        "artist": "Humlan Djojj, Josefine Götestam",
        "image": "https://i.scdn.co/image/ab67616d00001e02976c6bead0b037097e8fd858",
        "peak": "2",
        "prev": "101",
        "streak": "915",
        "streams": "86,809",
        "spotifyID": "0j2JcSeuF8ElJTrC8g6493"
    },
    {
        "ranking": "13",
        "title": "Fairytale of New York (feat. Kirsty MacColl)",
        "artist": "The Pogues, Kirsty MacColl",
        "image": "https://i.scdn.co/image/ab67616d00001e02d0ccf94a2d981db731f5dab8",
        "peak": "8",
        "prev": "9",
        "streak": "36",
        "streams": "84,688",
        "spotifyID": "3VTNVsTTu05dmTsVFrmGpK"
    },
    {
        "ranking": "14",
        "title": "Feliz Navidad",
        "artist": "José Feliciano",
        "image": "https://i.scdn.co/image/ab67616d00001e0257db4e3ca6a227ed612ad0b8",
        "peak": "3",
        "prev": "10",
        "streak": "40",
        "streams": "83,234",
        "spotifyID": "3qCeq0rWK67SoBDgFd2sId",
        "appleID": "feliz-navidad/255615879",
        "youtubeID": "N8NcQzMQN_U"
    },
    {
        "ranking": "15",
        "title": "It's Beginning to Look a Lot like Christmas",
        "artist": "Michael Bublé",
        "image": "https://i.scdn.co/image/ab67616d00001e022ead7786631d8dd3b59be4f0",
        "peak": "3",
        "prev": "8",
        "streak": "40",
        "streams": "82,545",
        "spotifyID": "1rv46mRwDqMEhOBZ7vODg3",
        "appleID": "its-beginning-to-look-a-lot-like-christmas/1592740089",
        "youtubeID": "QJ5DOWPGxwg"
    },
    {
        "ranking": "16",
        "title": "Driving Home for Christmas - 2019 Remaster",
        "artist": "Chris Rea",
        "image": "https://i.scdn.co/image/ab67616d00001e026d621c2d5114cc41c96b376a",
        "peak": "5",
        "prev": "12",
        "streak": "36",
        "streams": "80,481",
        "spotifyID": "27qAMKrDdKEs8HDXcvR24R"
    },
    {
        "ranking": "17",
        "title": "Ikväll Igen",
        "artist": "Bolaget",
        "image": "https://i.scdn.co/image/ab67616d00001e02806a186dbe661aef5e44ce65",
        "peak": "1",
        "prev": "—",
        "streak": "1",
        "streams": "80,378",
        "spotifyID": "4o5Ob60pz8QHcFKcr4MWyf"
    },
    {
        "ranking": "18",
        "title": "The Christmas Song (Merry Christmas To You)",
        "artist": "Nat King Cole",
        "image": "https://i.scdn.co/image/ab67616d00001e02deac5adf07affb5fec422701",
        "peak": "10",
        "prev": "16",
        "streak": "36",
        "streams": "79,999",
        "spotifyID": "5humEOJehpAwMJEJmb0JJ2",
        "youtubeID": "wKhRnZZ0cJI"
    },
    {
        "ranking": "19",
        "title": "That’s So True",
        "artist": "Gracie Abrams",
        "image": "https://i.scdn.co/image/ab67616d00001e021dac3694b3289cd903cb3acf",
        "peak": "2",
        "prev": "163",
        "streak": "67",
        "streams": "79,689",
        "spotifyID": "7ne4VBA60CxGM75vw0EYad",
        "appleID": "thats-so-true/1773474483",
        "youtubeID": "BDHM8cyJQa8"
    },
    {
        "ranking": "20",
        "title": "Hey Ho",
        "artist": "Freddy Kalas",
        "image": "https://i.scdn.co/image/ab67616d00001e02b3de07ca9d7f2219eeafab64",
        "peak": "3",
        "prev": "17",
        "streak": "37",
        "streams": "79,320",
        "spotifyID": "1ikAsZ38q8AQ1l7FcOhu5g",
        "appleID": "hey-ho/1613002527",
        "youtubeID": "joWd2P-6keM"
    },
    {
        "ranking": "21",
        "title": "Välkommen hem",
        "artist": "E.M.D.",
        "image": "https://i.scdn.co/image/ab67616d00001e027bfb06efd784e5443a4fa868",
        "peak": "7",
        "prev": "15",
        "streak": "37",
        "streams": "75,886",
        "spotifyID": "4WfSDuJ4MrpdSSCEOanwzD",
        "appleID": "v%C3%A4lkommen-hem/404517604",
        "youtubeID": "x7iF-gJ2G-o"
    },
    {
        "ranking": "22",
        "title": "APT.",
        "artist": "ROSÉ, Bruno Mars",
        "image": "https://i.scdn.co/image/ab67616d00001e02a9fb6e00986e42ad4764b1f3",
        "peak": "8",
        "prev": "175",
        "streak": "69",
        "streams": "75,362",
        "spotifyID": "4wJ5Qq0jBN4ajy7ouZIV1c",
        "youtubeID": "ekr2nIex040"
    },
    {
        "ranking": "23",
        "title": "Do They Know It's Christmas? - 1984 Version",
        "artist": "Band Aid",
        "image": "https://i.scdn.co/image/ab67616d00001e02d549b09f0264901929eaa6e8",
        "peak": "5",
        "prev": "18",
        "streak": "36",
        "streams": "74,818",
        "spotifyID": "4Yg2w0P29BBBMixyeNjDtj"
    },
    {
        "ranking": "24",
        "title": "Mer jul (Klassisk Version)",
        "artist": "Adolphson & Falk",
        "image": "https://i.scdn.co/image/ab67616d00001e029391393dcf907f702123b782",
        "peak": "4",
        "prev": "13",
        "streak": "36",
        "streams": "74,624",
        "spotifyID": "2UuBcEjO3nYMwS6rN84qDd",
        "appleID": "mer-jul/1592276358"
    },
    {
        "ranking": "25",
        "title": "Let It Snow! Let It Snow! Let It Snow!",
        "artist": "Dean Martin",
        "image": "https://i.scdn.co/image/ab67616d00001e026d88028a85c771f37374c8ea",
        "peak": "17",
        "prev": "26",
        "streak": "40",
        "streams": "74,525",
        "spotifyID": "2uFaJJtFpPDc5Pa95XzTvg",
        "appleID": "let-it-snow-let-it-snow-let-it-snow/1440830243",
        "youtubeID": "2TA3IKH8Y5c"
    },
    {
        "ranking": "26",
        "title": "White Christmas - 1947 Version",
        "artist": "Bing Crosby, Ken Darby Singers, John Scott Trotter & His Orchestra",
        "image": "https://i.scdn.co/image/ab67616d00001e028004cd6b343732b0e1e666f5",
        "peak": "6",
        "prev": "21",
        "streak": "8",
        "streams": "73,222",
        "spotifyID": "3XsaSIPWvM61RIFfeb0BBR"
    },
    {
        "ranking": "27",
        "title": "Kan Inte Gå",
        "artist": "Bolaget",
        "image": "https://i.scdn.co/image/ab67616d00001e02031ac25272d74c1b0b18c4de",
        "peak": "1",
        "prev": "—",
        "streak": "1",
        "streams": "73,157",
        "spotifyID": "6KOzO2mUwSwe8a9GiJAn7X"
    },
    {
        "ranking": "28",
        "title": "Babblarnas vaggvisa",
        "artist": "Babblarna",
        "image": "https://i.scdn.co/image/ab67616d00001e02c4a9b2f7b917402f799b1ecd",
        "peak": "1",
        "prev": "135",
        "streak": "1462",
        "streams": "72,506",
        "spotifyID": "3GygspQIcYy5OnRiw245Qh",
        "appleID": "babblarnas-vaggvisa/1597908525"
    },
    {
        "ranking": "29",
        "title": "Merry Christmas",
        "artist": "Ed Sheeran, Elton John",
        "image": "https://i.scdn.co/image/ab67616d00001e0276881e9e41989d99a205b169",
        "peak": "3",
        "prev": "23",
        "streak": "29",
        "streams": "71,206",
        "spotifyID": "0hz5PNF2wejwUKCMpesQWt",
        "appleID": "merry-christmas/1597450885",
        "youtubeID": "Q_yuO8UNGmY"
    },
    {
        "ranking": "30",
        "title": "Die With A Smile",
        "artist": "Lady Gaga, Bruno Mars",
        "image": "https://i.scdn.co/image/ab67616d00001e0282ea2e9e1858aa012c57cd45",
        "peak": "4",
        "prev": "177",
        "streak": "132",
        "streams": "70,507",
        "spotifyID": "2plbrEY59IikOBgBGLjaoe",
        "appleID": "die-with-a-smile/1762656732",
        "youtubeID": "kPa7bsKwL-c"
    },
    {
        "ranking": "31",
        "title": "Viva La Vida",
        "artist": "Soppgirobygget",
        "image": "https://i.scdn.co/image/ab67616d00001e02a768f2d563f8fd5c9b4f06f7",
        "peak": "2",
        "prev": "—",
        "streak": "1",
        "streams": "70,418",
        "spotifyID": "3PzfAzqI03wcX8OikTdrH2"
    },
    {
        "ranking": "32",
        "title": "Santa Tell Me",
        "artist": "Ariana Grande",
        "image": "https://i.scdn.co/image/ab67616d00001e02a1db745e63940bc06985dea5",
        "peak": "4",
        "prev": "19",
        "streak": "40",
        "streams": "69,294",
        "spotifyID": "0lizgQ7Qw35od7CYaoMBZb",
        "youtubeID": "nlR0MkrRklg"
    },
    {
        "ranking": "33",
        "title": "Ser du månen där du är ikväll? (Tillsammans igen)",
        "artist": "Thomas Stenström",
        "image": "https://i.scdn.co/image/ab67616d00001e02559425ccbaf87de4c52f3a07",
        "peak": "2",
        "prev": "30",
        "streak": "54",
        "streams": "69,174",
        "spotifyID": "4SLYrBfzgbLmiEdoKajyHL"
    },
    {
        "ranking": "34",
        "title": "Happy Xmas (War Is Over) - Remastered 2010",
        "artist": "John Lennon, Yoko Ono",
        "image": "https://i.scdn.co/image/ab67616d00001e0261a389971d7842d02b0623ab",
        "peak": "8",
        "prev": "20",
        "streak": "36",
        "streams": "68,229",
        "spotifyID": "27RYrbL6S02LNVhDWVl38b"
    },
    {
        "ranking": "35",
        "title": "Jag kommer hem igen till jul",
        "artist": "Peter Jöback",
        "image": "https://i.scdn.co/image/ab67616d00001e028e5cd147ee2e068f8de98d08",
        "peak": "17",
        "prev": "25",
        "streak": "35",
        "streams": "68,026",
        "spotifyID": "3eusN83SiYVrSA3hG4drFy",
        "appleID": "jag-kommer-hem-igen-till-jul/575417116"
    },
    {
        "ranking": "36",
        "title": "Mistletoe",
        "artist": "Justin Bieber",
        "image": "https://i.scdn.co/image/ab67616d00001e02af0aff7f601df9ed6d2d531d",
        "peak": "6",
        "prev": "24",
        "streak": "39",
        "streams": "66,114",
        "spotifyID": "7xapw9Oy21WpfEcib2ErSA",
        "appleID": "mistletoe/1440640717",
        "youtubeID": "LUjn3RpkcKY"
    },
    {
        "ranking": "37",
        "title": "Let It Snow! Let It Snow! Let It Snow! (with The B. Swanson Quartet)",
        "artist": "Frank Sinatra, B. Swanson Quartet",
        "image": "https://i.scdn.co/image/ab67616d00001e022e1e77d6acadd7e238d7bc42",
        "peak": "7",
        "prev": "22",
        "streak": "36",
        "streams": "64,169",
        "spotifyID": "0SUKNXEqZnRw7g0NO139FM"
    },
    {
        "ranking": "38",
        "title": "Juligen",
        "artist": "Just D",
        "image": "https://i.scdn.co/image/ab67616d00001e02d5bb99cd52da195675b2f2cd",
        "peak": "8",
        "prev": "27",
        "streak": "35",
        "streams": "61,743",
        "spotifyID": "1MMeScdLmniNyO4WMuoIxb",
        "appleID": "juligen/730710483"
    },
    {
        "ranking": "39",
        "title": "Lost and found",
        "artist": "Molly Sandén, Victor Leksell",
        "image": "https://i.scdn.co/image/ab67616d00001e02fd134e1b38d92c4c941421cc",
        "peak": "1",
        "prev": "—",
        "streak": "1",
        "streams": "60,769",
        "spotifyID": "5GdAGqF9ZI4gADtpVAxqe7"
    },
    {
        "ranking": "40",
        "title": "Cecilia Lind",
        "artist": "Yasin",
        "image": "https://i.scdn.co/image/ab67616d00001e02316a81cb43a85f2f6b7f5d33",
        "peak": "1",
        "prev": "198",
        "streak": "76",
        "streams": "57,944",
        "spotifyID": "1nPjwnKrO6imcSiaXNu8CX",
        "appleID": "cecilia-lind/1772906554",
        "youtubeID": "3dUgzKZV9jc"
    },
    {
        "ranking": "41",
        "title": "God jul - Feliz Navidad",
        "artist": "Lucianoz",
        "image": "https://i.scdn.co/image/ab67616d00001e02a025f9f7eb4c5dd05a9df5fc",
        "peak": "29",
        "prev": "29",
        "streak": "29",
        "streams": "55,358",
        "spotifyID": "7ewiV3hVXdDG1AdXEeh4sg",
        "youtubeID": "AIuc3eDcHPg"
    },
    {
        "ranking": "42",
        "title": "DNA",
        "artist": "Y4ska, Jireel, ROMANOS",
        "image": "https://i.scdn.co/image/ab67616d00001e02d0eef6cba6f3713028ab0d94",
        "peak": "2",
        "prev": "—",
        "streak": "1",
        "streams": "54,474",
        "spotifyID": "7HuBqX0G5mJTd8TEiPZ40K"
    },
    {
        "ranking": "43",
        "title": "O helga natt",
        "artist": "Tommy Körberg",
        "image": "https://i.scdn.co/image/ab67616d00001e026ce80817009552c78bc6157a",
        "peak": "11",
        "prev": "28",
        "streak": "27",
        "streams": "53,060",
        "spotifyID": "0XoGiZY2XtBW5qXB3ZzZOX"
    },
    {
        "ranking": "44",
        "title": "Sailor Song",
        "artist": "Gigi Perez",
        "image": "https://i.scdn.co/image/ab67616d00001e02e6065f209e0a01986206bd53",
        "peak": "4",
        "prev": "—",
        "streak": "1",
        "streams": "52,423",
        "spotifyID": "2262bWmqomIaJXwCRHr13j",
        "appleID": "1770187510",
        "youtubeID": "1lrFsXkT_rM"
    },
    {
        "ranking": "45",
        "title": "Nu tändas tusen juleljus",
        "artist": "Carola",
        "image": "https://i.scdn.co/image/ab67616d00001e02cafb95ecc39b580663d9c2bb",
        "peak": "18",
        "prev": "33",
        "streak": "33",
        "streams": "50,383",
        "spotifyID": "08D5bPhVLw01WdNchYxsqg",
        "appleID": "nu-t%C3%A4ndas-tusen-juleljus/268861996",
        "youtubeID": "JfT06kHnHQM"
    },
    {
        "ranking": "46",
        "title": "Happy Xmas (War Is Over)",
        "artist": "Céline Dion",
        "image": "https://i.scdn.co/image/ab67616d00001e023095cc2cb7ce3079685d4787",
        "peak": "22",
        "prev": "31",
        "streak": "35",
        "streams": "49,993",
        "spotifyID": "2ohR9Qj4TgZafZCptO9cly"
    },
    {
        "ranking": "47",
        "title": "Jul, jul strålande jul",
        "artist": "Carola",
        "image": "https://i.scdn.co/image/ab67616d00001e02cafb95ecc39b580663d9c2bb",
        "peak": "16",
        "prev": "32",
        "streak": "29",
        "streams": "49,818",
        "spotifyID": "33EVpTZhoyQw1mStrZTKfO",
        "appleID": "jul-jul-str%C3%A5lande-jul/268861531",
        "youtubeID": "qPhOtPiLPmo"
    },
    {
        "ranking": "48",
        "title": "Hallelujah",
        "artist": "Pentatonix",
        "image": "https://i.scdn.co/image/ab67616d00001e02345a0b7e0a608d66bec80d55",
        "peak": "28",
        "prev": "35",
        "streak": "35",
        "streams": "49,427",
        "spotifyID": "550rQQCGkrTzvp4SfpOPzx",
        "appleID": "hallelujah/1296455325",
        "youtubeID": "LRP8d7hhpoQ"
    },
    {
        "ranking": "49",
        "title": "Välkommen ner",
        "artist": "Bolaget",
        "image": "https://i.scdn.co/image/ab67616d00001e020ac0c89f055e4ba3bca16862",
        "peak": "1",
        "prev": "—",
        "streak": "1",
        "streams": "48,966",
        "spotifyID": "29YN98sTVSpfYMpPzFXaGU"
    },
    {
        "ranking": "50",
        "title": "Underneath the Tree",
        "artist": "Kelly Clarkson",
        "image": "https://i.scdn.co/image/ab67616d00001e029fd0d700bdf33c9ebc42f429",
        "peak": "37",
        "prev": "37",
        "streak": "36",
        "streams": "47,570",
        "spotifyID": "3nAp4IvdMPPWEH9uuXFFV5",
        "youtubeID": "EM2Fnp_qnE8"
    },
    {
        "ranking": "51",
        "title": "CALMA",
        "artist": "Y4ska, Dizzy",
        "image": "https://i.scdn.co/image/ab67616d00001e0259b698cec7db77189034a66b",
        "peak": "2",
        "prev": "—",
        "streak": "1",
        "streams": "47,330",
        "spotifyID": "0ZW2C4Yd8HvGXM6jrLmChx"
    },
    {
        "ranking": "52",
        "title": "Come Whatever, Come What May",
        "artist": "My Marianne, Jonathan Johansson",
        "image": "https://i.scdn.co/image/ab67616d00001e0296475073f97c862d0001b690",
        "peak": "26",
        "prev": "34",
        "streak": "28",
        "streams": "46,753",
        "spotifyID": "7h6dAktpx3MeQMfqN84JBW"
    },
    {
        "ranking": "53",
        "title": "Somna",
        "artist": "Humlan Djojj, Josefine Götestam",
        "image": "https://i.scdn.co/image/ab67616d00001e02976c6bead0b037097e8fd858",
        "peak": "13",
        "prev": "—",
        "streak": "1",
        "streams": "45,683",
        "spotifyID": "401N7rbd6MSziVSDVTaQr7"
    },
    {
        "ranking": "54",
        "title": "BIRDS OF A FEATHER",
        "artist": "Billie Eilish",
        "image": "https://i.scdn.co/image/ab67616d00001e0271d62ea7ea8a5be92d3c1f62",
        "peak": "4",
        "prev": "—",
        "streak": "1",
        "streams": "45,619",
        "spotifyID": "6dOtVTDdiauQNBQEDOtlAB",
        "youtubeID": "V9PVRfjEBTI"
    },
    {
        "ranking": "55",
        "title": "A Bar Song (Tipsy)",
        "artist": "Shaboozey",
        "image": "https://i.scdn.co/image/ab67616d00001e0260df033c8f8b17384387666a",
        "peak": "1",
        "prev": "—",
        "streak": "1",
        "streams": "44,923",
        "spotifyID": "5fZJQrFKWQLb7FpJXZ1g7K",
        "appleID": "a-bar-song-tipsy/1737085899",
        "youtubeID": "t7bQwwqW-Hc"
    },
    {
        "ranking": "56",
        "title": "Ole Dole Doff",
        "artist": "Asme, Shiro",
        "image": "https://i.scdn.co/image/ab67616d00001e023808b9a08f03ad79a99da5fe",
        "peak": "1",
        "prev": "—",
        "streak": "1",
        "streams": "44,349",
        "spotifyID": "0Pii5EXqXhPOTcX86zDxaW"
    },
    {
        "ranking": "57",
        "title": "Sleigh Ride",
        "artist": "The Ronettes",
        "image": "https://i.scdn.co/image/ab67616d00001e021f0d5a8ff630fd5944c3936d",
        "peak": "33",
        "prev": "40",
        "streak": "28",
        "streams": "43,840",
        "spotifyID": "7fUYUcWy853HS8YJn0b3Sr",
        "appleID": "sleigh-ride/336037282",
        "youtubeID": "DkXIJe8CaIc"
    },
    {
        "ranking": "58",
        "title": "Hey Ho",
        "artist": "Aslak Trude",
        "image": "https://i.scdn.co/image/ab67616d00001e02ad40667bc5343f1e1b684b8b",
        "peak": "23",
        "prev": "43",
        "streak": "36",
        "streams": "43,781",
        "spotifyID": "1mlP7iqVLZMYryuispoFBE",
        "appleID": "hey-ho/1588723406",
        "youtubeID": "k2Qm4IM_zFY"
    },
    {
        "ranking": "59",
        "title": "Stjärnorna",
        "artist": "Humlan Djojj, Josefine Götestam",
        "image": "https://i.scdn.co/image/ab67616d00001e02976c6bead0b037097e8fd858",
        "peak": "16",
        "prev": "—",
        "streak": "1",
        "streams": "43,595",
        "spotifyID": "5jlAu4lHHVzheutRcbDklk"
    },
    {
        "ranking": "60",
        "title": "Regnblöta skor",
        "artist": "Miriam Bryant",
        "image": "https://i.scdn.co/image/ab67616d00001e021e996bf17a19bb4039292808",
        "peak": "1",
        "prev": "—",
        "streak": "1",
        "streams": "43,405",
        "spotifyID": "2YYsb4d39JKLpQgTMpXOQ0"
    },
    {
        "ranking": "61",
        "title": "Fitta och kebab",
        "artist": "Prilla Generalen",
        "image": "https://i.scdn.co/image/ab67616d00001e02ba28c7cce1b76b4ac84ab3a4",
        "peak": "11",
        "prev": "—",
        "streak": "1",
        "streams": "42,508",
        "spotifyID": "1H3okcaLb3IjLnp05KrRaD"
    },
    {
        "ranking": "62",
        "title": "Tomten, jag vill ha en riktig jul",
        "artist": "Judit",
        "image": "https://i.scdn.co/image/ab67616d00001e0230fe2234d847f29124062fc8",
        "peak": "11",
        "prev": "39",
        "streak": "37",
        "streams": "41,939",
        "spotifyID": "520Jrg250xi0QXIKxFqK4n"
    },
    {
        "ranking": "63",
        "title": "Bærum Bitches (Mannschaft)",
        "artist": "Søte og Rare Gutter",
        "image": "https://i.scdn.co/image/ab67616d00001e027a4518001e82312f9bffe806",
        "peak": "3",
        "prev": "—",
        "streak": "1",
        "streams": "41,922",
        "spotifyID": "3ZNOlf3hO8Lhnpvg2iF16D"
    },
    {
        "ranking": "64",
        "title": "Julen är här",
        "artist": "Lucianoz",
        "image": "https://i.scdn.co/image/ab67616d00001e020ffe63eb68b00107e4afaba3",
        "peak": "39",
        "prev": "41",
        "streak": "30",
        "streams": "41,258",
        "spotifyID": "2c2TR5vF0vTAgyKUfer5Gb",
        "youtubeID": "6wcphB-uFvg"
    },
    {
        "ranking": "65",
        "title": "Blue Christmas",
        "artist": "Elvis Presley",
        "image": "https://i.scdn.co/image/ab67616d00001e02aa509be2dd24fb6c753cf292",
        "peak": "24",
        "prev": "44",
        "streak": "26",
        "streams": "41,248",
        "spotifyID": "3QiAAp20rPC3dcAtKtMaqQ",
        "appleID": "blue-christmas/676288368"
    },
    {
        "ranking": "66",
        "title": "Bad Dreams",
        "artist": "Teddy Swims",
        "image": "https://i.scdn.co/image/ab67616d00001e02de4b0388cb6e5267132a07bc",
        "peak": "8",
        "prev": "—",
        "streak": "1",
        "streams": "41,065",
        "spotifyID": "3nHuKdFJZm78CoeBnDcFKe",
        "appleID": "bad-dreams/1765799904",
        "youtubeID": "Qh8QwVYOSVU"
    },
    {
        "ranking": "67",
        "title": "SANTA",
        "artist": "Amanda Jenssen",
        "image": "https://i.scdn.co/image/ab67616d00001e0291b939559ce113562d82da68",
        "peak": "36",
        "prev": "36",
        "streak": "9",
        "streams": "40,372",
        "spotifyID": "2jYXF2eyXVOAnREXGKzuvD"
    },
    {
        "ranking": "68",
        "title": "Vanilj",
        "artist": "BoBa, Malik Dalasi",
        "image": "https://i.scdn.co/image/ab67616d00001e024001be304e5d014e1a78e79b",
        "peak": "4",
        "prev": "—",
        "streak": "1",
        "streams": "39,700",
        "spotifyID": "2CBuonjhTSzjzDBKNhjxlF"
    },
    {
        "ranking": "69",
        "title": "Stad i ljus",
        "artist": "Tommy Körberg",
        "image": "https://i.scdn.co/image/ab67616d00001e02ea718cef99b43189becc5975",
        "peak": "35",
        "prev": "51",
        "streak": "28",
        "streams": "39,664",
        "spotifyID": "7bVwUOySQGO2afJ0LArAMi",
        "appleID": "stad-i-ljus/324171216",
        "youtubeID": "GO9VUhn1TXk"
    },
    {
        "ranking": "70",
        "title": "Messy",
        "artist": "Lola Young",
        "image": "https://i.scdn.co/image/ab67616d00001e026aa2a180c7b009ca8454ef89",
        "peak": "40",
        "prev": "—",
        "streak": "1",
        "streams": "38,998",
        "spotifyID": "35ISBknsCeZQtq66xABI9g",
        "appleID": "messy/1743250261",
        "youtubeID": "k-k2_Liofy8"
    },
    {
        "ranking": "71",
        "title": "Lose Control",
        "artist": "Teddy Swims",
        "image": "https://i.scdn.co/image/ab67616d00001e021a0323cc23419360a34a3ace",
        "peak": "14",
        "prev": "—",
        "streak": "1",
        "streams": "38,904",
        "spotifyID": "17phhZDn6oGtzMe56NuWvj",
        "appleID": "lose-control/1691699836",
        "youtubeID": "GZ3zL7kT6_c"
    },
    {
        "ranking": "72",
        "title": "Hej mitt vinterland",
        "artist": "Carola",
        "image": "https://i.scdn.co/image/ab67616d00001e0208d32250b485430b3d9ba1f3",
        "peak": "38",
        "prev": "38",
        "streak": "28",
        "streams": "38,826",
        "spotifyID": "6zsRlxuaMDtffiAk9FtkUg"
    },
    {
        "ranking": "73",
        "title": "Holly Jolly Christmas",
        "artist": "Michael Bublé",
        "image": "https://i.scdn.co/image/ab67616d00001e022ead7786631d8dd3b59be4f0",
        "peak": "29",
        "prev": "54",
        "streak": "36",
        "streams": "38,641",
        "spotifyID": "67mgz7S5y7hnCE63YBjfO6",
        "appleID": "holly-jolly-christmas/1782947597"
    },
    {
        "ranking": "74",
        "title": "BAILA",
        "artist": "Gaboro, ROMANOS",
        "image": "https://i.scdn.co/image/ab67616d00001e0211f81b773b13cb2eee614350",
        "peak": "60",
        "prev": "—",
        "streak": "1",
        "streams": "38,023",
        "spotifyID": "5BGCXuJmVIDnYcCCHWCizV"
    },
    {
        "ranking": "75",
        "title": "Den vintertid nu kommer",
        "artist": "Miss Li",
        "image": "https://i.scdn.co/image/ab67616d00001e0202345cc5f42c00275382b8b8",
        "peak": "23",
        "prev": "47",
        "streak": "27",
        "streams": "37,732",
        "spotifyID": "0hSBZP9SodLCOLWmfgK9MK",
        "appleID": "den-vintertid-nu-kommer/1438634447"
    },
    {
        "ranking": "76",
        "title": "Beautiful Things",
        "artist": "Benson Boone",
        "image": "https://i.scdn.co/image/ab67616d00001e02cc04ff3e70e146ba9abacf40",
        "peak": "3",
        "prev": "—",
        "streak": "1",
        "streams": "37,242",
        "spotifyID": "3xkHsmpQCBMytMJNiDf3Ii",
        "youtubeID": "Oa_RSwwpPaA"
    },
    {
        "ranking": "77",
        "title": "Decembernatt (Halleluja)",
        "artist": "Peter Jöback",
        "image": "https://i.scdn.co/image/ab67616d00001e028e5cd147ee2e068f8de98d08",
        "peak": "14",
        "prev": "46",
        "streak": "27",
        "streams": "37,214",
        "spotifyID": "3b6mt8vlFS89uRx7kgKhkb"
    },
    {
        "ranking": "78",
        "title": "Carol of the Bells",
        "artist": "John Williams",
        "image": "https://i.scdn.co/image/ab67616d00001e02f497846e25233023ca7cb8b1",
        "peak": "56",
        "prev": "56",
        "streak": "16",
        "streams": "37,187",
        "spotifyID": "4tHqQMWSqmL6YjXwsqthDI",
        "appleID": "carol-of-the-bells/1049529730"
    },
    {
        "ranking": "79",
        "title": "It's Beginning to Look a Lot Like Christmas (with Mitchell Ayres & His Orchestra)",
        "artist": "Perry Como, The Fontane Sisters, Mitchell Ayres & His Orchestra",
        "image": "https://i.scdn.co/image/ab67616d00001e027a5e4ed28aeceac63ae4b043",
        "peak": "40",
        "prev": "45",
        "streak": "28",
        "streams": "37,099",
        "spotifyID": "6IeK3Ap5m3HabwJxgI6eSE"
    },
    {
        "ranking": "80",
        "title": "Nu säger vi godnatt",
        "artist": "Humlan Djojj, Josefine Götestam",
        "image": "https://i.scdn.co/image/ab67616d00001e02976c6bead0b037097e8fd858",
        "peak": "20",
        "prev": "—",
        "streak": "1",
        "streams": "36,265",
        "spotifyID": "7qLwjBWh3M2JLFlEokIjUP"
    },
    {
        "ranking": "81",
        "title": "Suavemente",
        "artist": "Gaboro",
        "image": "https://i.scdn.co/image/ab67616d00001e027e39612020ae042a451b9363",
        "peak": "44",
        "prev": "—",
        "streak": "1",
        "streams": "36,166",
        "spotifyID": "0wqHIqVLDIRjJqvm8nmiG4"
    },
    {
        "ranking": "82",
        "title": "Timeless (with Playboi Carti)",
        "artist": "The Weeknd, Playboi Carti",
        "image": "https://i.scdn.co/image/ab67616d00001e0294f662ef3b5677376d8a78d4",
        "peak": "4",
        "prev": "—",
        "streak": "1",
        "streams": "35,915",
        "spotifyID": "1Es7AUAhQvapIcoh3qMKDL",
        "appleID": "timeless/1770380890",
        "youtubeID": "5EpyN_6dqyk"
    },
    {
        "ranking": "83",
        "title": "Under the Tree (from “That Christmas”)",
        "artist": "Ed Sheeran",
        "image": "https://i.scdn.co/image/ab67616d00001e028c5e02d9f4bfa29203cd3310",
        "peak": "40",
        "prev": "42",
        "streak": "27",
        "streams": "35,515",
        "spotifyID": "3emyfamOMxgrus8oZQh6Mx"
    },
    {
        "ranking": "84",
        "title": "Dum",
        "artist": "Bolaget",
        "image": "https://i.scdn.co/image/ab67616d00001e0245e4dd98e1aa1b1d99fd816d",
        "peak": "16",
        "prev": "—",
        "streak": "1",
        "streams": "35,428",
        "spotifyID": "3fneVsIBA5RkkXsQhOW7pn"
    },
    {
        "ranking": "85",
        "title": "Gläns över sjö och strand",
        "artist": "Sofia Källgren",
        "image": "https://i.scdn.co/image/ab67616d00001e02500b6a2d5f1b5ed01db5afe6",
        "peak": "32",
        "prev": "53",
        "streak": "9",
        "streams": "34,526",
        "spotifyID": "4pdnPqZ6NOnofNfOOEO0iz"
    },
    {
        "ranking": "86",
        "title": "Christmas Lights",
        "artist": "Coldplay",
        "image": "https://i.scdn.co/image/ab67616d00001e025f30d36db3dd22681531d1da",
        "peak": "46",
        "prev": "55",
        "streak": "26",
        "streams": "34,410",
        "spotifyID": "4fzyvSu73BhGvi96p2zwjL",
        "appleID": "christmas-lights/693526009"
    },
    {
        "ranking": "87",
        "title": "I Might",
        "artist": "Sarettii",
        "image": "https://i.scdn.co/image/ab67616d00001e0268adff83cc3912410b3767ac",
        "peak": "1",
        "prev": "—",
        "streak": "1",
        "streams": "34,386",
        "spotifyID": "2UX821OXiIYGp67PdMqmoe"
    },
    {
        "ranking": "88",
        "title": "Merry Christmas Everyone",
        "artist": "Shakin' Stevens",
        "image": "https://i.scdn.co/image/ab67616d00001e02d962f3b4235f8c6429a829fb",
        "peak": "34",
        "prev": "50",
        "streak": "28",
        "streams": "34,280",
        "spotifyID": "2TE4xW3ImvpltVU0cPcKUn",
        "appleID": "merry-christmas-everyone/347010852",
        "youtubeID": "ZeyHl1tQeaQ"
    },
    {
        "ranking": "89",
        "title": "Raggar-Ren",
        "artist": "Albatraoz",
        "image": "https://i.scdn.co/image/ab67616d00001e02559c6dc64f8f94cc2e66501c",
        "peak": "41",
        "prev": "67",
        "streak": "27",
        "streams": "34,143",
        "spotifyID": "1AU50cPvCOvuSrQ6CI1R2n"
    },
    {
        "ranking": "90",
        "title": "Espresso",
        "artist": "Sabrina Carpenter",
        "image": "https://i.scdn.co/image/ab67616d00001e02fd8d7a8d96871e791cb1f626",
        "peak": "3",
        "prev": "—",
        "streak": "1",
        "streams": "33,912",
        "spotifyID": "2HRqTpkrJO5ggZyyK6NPWz",
        "youtubeID": "eVli-tstM5E"
    },
    {
        "ranking": "91",
        "title": "Låt Mig Va",
        "artist": "Bolaget, Victor Leksell",
        "image": "https://i.scdn.co/image/ab67616d00001e02a126ab76c7171e0819c617bb",
        "peak": "1",
        "prev": "—",
        "streak": "1",
        "streams": "33,826",
        "spotifyID": "6Vbgg3C5Qo7olhjIIr1r4e"
    },
    {
        "ranking": "92",
        "title": "Armani",
        "artist": "Jireel",
        "image": "https://i.scdn.co/image/ab67616d00001e02891f949dda5372722f59570c",
        "peak": "1",
        "prev": "—",
        "streak": "1",
        "streams": "33,642",
        "spotifyID": "5avYou6QKMsC1nnbOkqqm9"
    },
    {
        "ranking": "93",
        "title": "Godnattvisan",
        "artist": "Humlan Djojj, Josefine Götestam",
        "image": "https://i.scdn.co/image/ab67616d00001e02976c6bead0b037097e8fd858",
        "peak": "29",
        "prev": "—",
        "streak": "1",
        "streams": "32,851",
        "spotifyID": "5MxHurfskrN1RvkKez2ofd"
    },
    {
        "ranking": "94",
        "title": "Egotrip",
        "artist": "Fjellrev",
        "image": "https://i.scdn.co/image/ab67616d00001e020c324816bbaf6206b95819c3",
        "peak": "94",
        "prev": "—",
        "streak": "1",
        "streams": "32,711",
        "spotifyID": "6C3zo1ZwpVX8J5WTRr3j9l"
    },
    {
        "ranking": "95",
        "title": "RIKERUD",
        "artist": "Soppgirobygget",
        "image": "https://i.scdn.co/image/ab67616d00001e0265fca6c153f2c5afeb16feef",
        "peak": "50",
        "prev": "—",
        "streak": "1",
        "streams": "32,142",
        "spotifyID": "2PYZBeiZ6ofXQR0Ql7BuGS"
    },
    {
        "ranking": "96",
        "title": "Nu är det jul",
        "artist": "Arvingarna",
        "image": "https://i.scdn.co/image/ab67616d00001e027b90d8ad0eea3fbfeb48efdd",
        "peak": "55",
        "prev": "58",
        "streak": "14",
        "streams": "31,868",
        "spotifyID": "4oYnR53QmxTibIUMUymnhE"
    },
    {
        "ranking": "97",
        "title": "VEM FAN E DU?",
        "artist": "Hooja, Miriam Bryant",
        "image": "https://i.scdn.co/image/ab67616d00001e020d307f0c1d466a1ed94c15d6",
        "peak": "1",
        "prev": "—",
        "streak": "1",
        "streams": "31,318",
        "spotifyID": "4BliCq54T5TbxmaLdXJGEK"
    },
    {
        "ranking": "98",
        "title": "Jingle Bells - Remastered 1999",
        "artist": "Frank Sinatra",
        "image": "https://i.scdn.co/image/ab67616d00001e0294fd2e614d0862bdd2592594",
        "peak": "55",
        "prev": "57",
        "streak": "16",
        "streams": "31,291",
        "spotifyID": "4HEOgBHRCExyYVeTyrXsnL"
    },
    {
        "ranking": "99",
        "title": "Christmas (Baby Please Come Home)",
        "artist": "Michael Bublé",
        "image": "https://i.scdn.co/image/ab67616d00001e022ead7786631d8dd3b59be4f0",
        "peak": "24",
        "prev": "48",
        "streak": "14",
        "streams": "30,593",
        "spotifyID": "66WPXyhXqMlkM1kZhyEXWK"
    },
    {
        "ranking": "100",
        "title": "Indigo (feat. Avery Anna)",
        "artist": "Sam Barber, Avery Anna",
        "image": "https://i.scdn.co/image/ab67616d00001e02c944a2c490ed24e29eef5119",
        "peak": "73",
        "prev": "—",
        "streak": "1",
        "streams": "30,341",
        "spotifyID": "1KZG1H1OCugGqIRmk1wF9m"
    }
]